{
  "id": "9289e368-7fe5-4554-9417-aac9013feaa6-11",
  "organizationId": "c84cc031-eb06-4ff4-b8c2-aac901384b95",
  "folderId": null,
  "type": 4,
  "name": "monsieur mr",
  "notes": null,
  "favorite": false,
  "identity": {
    "title": null,
    "firstName": "monsieur",
    "middleName": null,
    "lastName": "",
    "address1": "Adresse",
    "address2": null,
    "address3": null,
    "city": "City",
    "state": "Région",
    "postalCode": "62000",
    "country": "France",
    "company": "robbin",
    "email": "unknow@mail.com",
    "phone": "0000000000",
    "ssn": null,
    "username": "monsieur mr",
    "passportNumber": null,
    "licenseNumber": null
  },
  "collectionIds": [
    "4da02579-376c-464f-841c-aac9013feaa6"
  ]
},
